[
  {
    "dni": "74076421",
    "tipo": "entrada",
    "fecha": "2025-10-20",
    "hora": "18:15:26.773143",
    "timestamp": "2025-10-20T18:15:26.774906",
    "intentos_sincronizacion": 10,
    "fecha_error": "2025-10-21T13:02:22.722397"
  },
  {
    "dni": "74076421",
    "tipo": "entrada",
    "fecha": "2025-10-20",
    "hora": "18:15:55.202181",
    "timestamp": "2025-10-20T18:15:55.204210",
    "intentos_sincronizacion": 10,
    "fecha_error": "2025-10-21T13:02:22.724139"
  },
  {
    "dni": "74076421",
    "tipo": "entrada",
    "fecha": "2025-10-20",
    "hora": "18:27:16.035904",
    "timestamp": "2025-10-20T18:27:16.037616",
    "intentos_sincronizacion": 10,
    "fecha_error": "2025-10-21T13:02:22.725701"
  },
  {
    "dni": "74076421",
    "tipo": "entrada",
    "fecha": "2025-10-20",
    "hora": "18:27:40.522679",
    "timestamp": "2025-10-20T18:27:40.524067",
    "intentos_sincronizacion": 10,
    "fecha_error": "2025-10-21T13:02:22.727404"
  },
  {
    "dni": "74076421",
    "tipo": "entrada",
    "fecha": "2025-10-20",
    "hora": "18:27:54.419820",
    "timestamp": "2025-10-20T18:27:54.421082",
    "intentos_sincronizacion": 10,
    "fecha_error": "2025-10-21T13:02:22.728873"
  },
  {
    "dni": "74076421",
    "tipo": "entrada",
    "fecha": "2025-10-21",
    "hora": "15:37:13",
    "timestamp": "2025-10-21T15:37:13.842566",
    "intentos_sincronizacion": 10,
    "fecha_error": "2025-10-21T15:44:02.079289"
  }
]